colebrook/__init__.py
colebrook/colebrook.py
colebrook-0.0.5.dist-info/LICENSE
colebrook-0.0.5.dist-info/METADATA
colebrook-0.0.5.dist-info/WHEEL
colebrook-0.0.5.dist-info/top_level.txt
colebrook-0.0.5.dist-info/RECORD
