Metadata-Version: 2.1
Name: colebrook
Version: 0.0.5
Summary: A small module that calculate colebrook-white approximations
Home-page: https://github.com/IMEConsultants/colebrook/
Author: Rob Markoski
Author-email: software@imeconsultants.com.au
License: UNKNOWN
Platform: UNKNOWN
Classifier: Programming Language :: Python :: 3
Classifier: License :: OSI Approved :: GNU Lesser General Public License v3 (LGPLv3)
Classifier: Operating System :: OS Independent
